[
    
{   "id":1,
    "name":"cityam",
    "website":"https://www.cityam.com/",
    "address":"https://www.cityam.com/london-must-become-a-world-leader-on-climate-change-action/",
    "base":"https://www.cityam.com/"
},
{   "id":2,
    "name":"thetimes",
    "website":"https://www.thetimes.com/",
    "address":"https://www.thetimes.co.uk/environment/climate-change",
    "base":"https://www.thetimes.com/"
},
{   "id":3,
    "name":"theguardian",
    "website":"https://www.theguardian.com/",
    "address":"https://www.theguardian.com/environment/climate-crisis",
    "base":"https://www.theguardian.com/"
},
{   "id":4,
    "name":"the new york times",
    "website":"https://www.nytimes.com/",
    "address":"https://www.nytimes.com/international/section/climate",
    "base":"https://www.nytimes.com/"
},
{   "id":5,
    "name":"latimes",
    "website":"https://www.latimes.com/",
    "address":"https://www.latimes.com/environment",
    "base":"https://www.latimes.com/"
},
{   "id":6,
    "name":"smh",
    "website":"https://www.smh.com.au/",
    "address":"https://www.smh.com.au/environment/climate-change",
    "base":"https://www.smh.com.au"
},
{   "id":7,
    "name":"un",
    "website":"https://www.un.org/",
    "address":"https://www.un.org/climatechange",
    "base":"https://www.un.org/"
},
{   "id":8,
    "name":"bbc",
    "website":"https://www.bbc.co.uk",
    "address":"https://www.bbc.co.uk/news/science_and_environment",
    "base":"https://www.bbc.co.uk"
},
{   "id":9,
    "name":"es",
    "website":"https://www.standard.co.uk",
    "address":"https://www.standard.co.uk/topic/climate-change",
    "base":"https://www.standard.co.uk"
},
{   "id":10,
    "name":"sun",
    "website":"https://www.thesun.co.uk/",
    "address":"https://www.thesun.co.uk/topic/climate-change-environment/",
    "base":"https://www.thesun.co.uk/"
},
{   "id":11,
    "name":"dm",
    "website":"https://www.dailymail.co.uk/",
    "address":"https://www.dailymail.co.uk/news/climate_change_global_warming/index.html",
    "base":"https://www.dailymail.co.uk/"
},
{   "id":12,
    "name":"nyp",
    "website":"https://nypost.com/",
    "address":"https://nypost.com/tag/climate-change/",
    "base":"https://nypost.com/"
},
{   "id":13,
    "name":"telegraph",
    "website":"https://www.telegraph.co.uk/",
    "address":"https://www.telegraph.co.uk/climate-change",
    "base":"https://www.telegraph.co.uk/"
},
{   "id":14,
    "name":"Nature Climate Change",
    "website":"https://www.nature.com/",
    "address":"https://www.nature.com/nclimate/",
    "base":"https://www.nature.com/"
},
{   "id":15,
    "name":"Sustainable GW",
    "website":"https://www.planetforward.org/",
    "address":"https://www.planetforward.org/",
    "base":"https://www.planetforward.org/"
},
{   "id":16,
    "name":"Climate Science & Policy Watch",
    "website":"https://whistleblower.org/",
    "address":"https://whistleblower.org/climate-science-watch/",
    "base":"https://whistleblower.org/"
},
{   "id":17,
    "name":"Climate Science & Policy Watch",
    "website":"https://whistleblower.org/",
    "address":"https://whistleblower.org/climate-science-watch/",
    "base":"https://whistleblower.org/"
},
{   "id":18,
    "name":"DeSmog",
    "website":"https://www.desmog.com/",
    "address":"https://www.desmog.com/?s=climate+change&jet_ajax_search_settings=%7B%22search_source%22%3A%5B%22post%22%2C%22entry%22%2C%22series%22%2C%22database%22%5D%2C%22search_taxonomy%22%3A%22topic%22%2C%22results_order_by%22%3A%22relevance%22%2C%22results_order%22%3A%22desc%22%2C%22sentence%22%3A%22yes%22%7D&post_type=post%2Centry%2Cseries%2Cdatabase&jet_ajax_search_categories=0",
    "base":"https://www.desmog.com/"
},
{   "id":19,
    "name":"Ask NASA” Climate Blog",
    "website":"https://climate.nasa.gov/",
    "address":"https://climate.nasa.gov/ask-nasa-climate/",
    "base":"https://climate.nasa.gov/"
},
{   "id":20,
    "name":"Climatelinks",
    "website":"https://www.climatelinks.org/",
    "address":"https://www.climatelinks.org/blog",
    "base":"https://www.climatelinks.org/"
},
{   "id":21,
    "name":"NOAA Climate.gov",
    "website":"https://www.climate.gov/",
    "address":"https://www.climate.gov/",
    "base":"https://www.climate.gov/"
},
{   "id":22,
    "name":"AccuWeather Climate Change Center",
    "website":"https://www.accuweather.com/",
    "address":"https://www.accuweather.com/en/weather-blogs/climatechange",
    "base":"https://www.accuweather.com/"
},
{   "id":23,
    "name":"Climate Central",
    "website":"https://www.climatecentral.org/",
    "address":"https://www.climatecentral.org/",
    "base":"https://www.climatecentral.org/"
},
{   "id":24,
    "name":"Climate Home News",
    "website":"https://www.climatechangenews.com/",
    "address":"https://www.climatechangenews.com/",
    "base":"https://www.climatechangenews.com/"
},
{   "id":25,
    "name":"Climate Wire",
    "website":"https://www.eenews.net/",
    "address":"https://www.eenews.net/publication/climatewire/",
    "base":"https://www.eenews.net/"
},
{   "id":26,
    "name":"Climate Central",
    "website":"https://www.climatecentral.org/",
    "address":"https://www.climatecentral.org/",
    "base":"https://www.climatecentral.org/"
},
{   "id":27,
    "name":"The Daily Climate",
    "website":"https://www.dailyclimate.org/",
    "address":"https://www.dailyclimate.org/",
    "base":"https://www.dailyclimate.org/"
},
{   "id":28,
    "name":"Environmental Health News (EHN)",
    "website":"https://www.ehn.org/",
    "address":"https://www.ehn.org/",
    "base":"https://www.ehn.org/"
},
{   "id":29,
    "name":"EcoWatch",
    "website":"https://www.ecowatch.com/",
    "address":"https://www.ecowatch.com/",
    "base":"https://www.ecowatch.com/"
},
{   "id":30,
    "name":"Grist",
    "website":"https://grist.org/",
    "address":"https://grist.org/",
    "base":"https://grist.org/"
},
{   "id":31,
    "name":"Testing",
    "website":"https://www.dailyclimate.org/",
    "address":"https://www.dailyclimate.org/",
    "base":"https://www.dailyclimate.org/"
},
{   "id":32,
    "name":"testing2",
    "website":"https://www.dailyclimate.org/",
    "address":"https://www.dailyclimate.org/",
    "base":"https://www.dailyclimate.org/"
},
{   "id":33,
    "name":"cityam",
    "website":"https://www.cityam.com/",
    "address":"https://www.cityam.com/london-must-become-a-world-leader-on-climate-change-action/",
    "base":"https://www.cityam.com/"
},
{   "id":34,
    "name":"CCityam",
    "website":"https://www.cityam.com/",
    "address":"https://www.cityam.com/london-must-become-a-world-leader-on-climate-change-action/",
    "base":"https://www.cityam.com/"}]